{
  "model": "Kimi-K2.5",
  "num_players": 5,
  "num_rounds": 5,
  "round_results": [
    {
      "round": 1,
      "choices": {
        "Player 1": 22,
        "Player 2": 22,
        "Player 3": 25,
        "Player 4": 18,
        "Player 5": 20
      },
      "average": 21.4,
      "target": 10.7,
      "winner": "Player 4",
      "thoughts": {
        "Player 1": "这是第一轮游戏，没有任何历史信息可以参考。我需要分析这个博弈的结构：\n\n目标值 = 0.5 × (五人平均值) = 0.5 × (总和/5) = 总和/10\n\n如果所有玩家都选择相同的数字 x，那么目标值 = (5x)/10 = 0.5x，所以最优选择应该是 0.5x。但如果大家都理性地选择 0.5x，那么新的目标值又变成 0.25x，依此类推，这会导致向0收敛的迭代过程。\n\n在经典的\"选平均数的2/3\"博弈中，理性推理会导致选择接近0。但这里是\"选平均数的1/2\"，收敛速度更快。\n\n然而，现实中玩家不会完全理性：\n1. 有些玩家可能不理解规则，随机选择\n2. 有些玩家可能选择中间值50\n3. 有些玩家可能进行多步推理\n\n作为第一轮，我需要做一个平衡的选择：\n- 如果大家都选50，目标值是25\n- 如果大家都理性地选25，目标值是12.5\n- 如果进行两步推理，选12.5，目标值是6.25\n\n考虑到混合策略，选择15-25之间比较安全。我选择22，这是一个介于 naive (50) 和理性推理结果之间的值，既能应对部分理性玩家，也能在其他人选择较高数字时有竞争力。",
        "Player 2": "这是第1轮，我没有历史信息可以参考。让我分析这个游戏：\n\n目标 = 0.5 × (五人数字之和 / 5) = (五人数字之和) / 10\n\n如果所有玩家都随机选择0-100，平均值约50，那么目标约25。\n\n但这涉及到博弈论中的「选美比赛」问题：每个玩家都想预测别人的选择，然后选择那个预测值的0.5倍。\n\n- 如果大家都理性，会想：别人平均选50，我应该选25\n- 但如果别人也想到了这一点，他们会选25，那么目标就是12.5\n- 继续迭代：25→12.5→6.25→3.125...\n\n理论上理性玩家的均衡趋近于0。但在实际游戏中，并非所有玩家都完全理性。\n\n作为第一轮，我需要平衡：\n- 如果选太高（如50），别人选低的话我会输\n- 如果选太低（如0），别人选中等值的话我也会输\n\n一个合理的策略是选择一个中等偏低的值，比如20-30之间，既考虑了部分理性玩家会选低值，也考虑了可能有非理性的高值选择。我选择22，这是一个在第一轮相对安全的中间策略。",
        "Player 3": "这是第1轮，没有任何历史信息。我需要分析这个博弈：\n\n目标值 = 0.5 × (五人数字平均值) = 0.5 × (总和/5) = 总和/10\n\n如果所有5名玩家都随机选择0-100，平均值约50，目标值约25。\n\n但这是一个典型的\"选美竞赛\"博弈（凯恩斯选美竞赛）：\n- 第一层思维：随机选，目标≈25\n- 第二层思维：别人也这么想，大家都选25，目标≈12.5\n- 第三层思维：别人也这么想，大家都选12.5，目标≈6.25\n- ... 收敛到0\n\n然而现实中，玩家不会完全理性迭代到0。通常实验结果在20-30之间。\n\n作为Player 3，我需要在第一轮建立信息。选择一个中等偏低的数字，既不太激进（选0），也不太保守（选50）。\n\n考虑到：\n- 如果有玩家选0-10的极端低值，会拉低平均值\n- 如果有玩家选50+的高值，会拉高平均值\n- 最可能的情况是多数人选择20-40区间\n\n我选择25，这是一个经典的第一轮策略，位于第一层和第二层思维的中间位置。",
        "Player 4": "这是第一轮游戏，没有任何历史数据可以参考。我需要分析这个博弈的结构：\n\n目标值 = 0.5 × (五人数之和 / 5) = (五人数之和) / 10\n\n这是一个典型的\"选美竞赛\"博弈。如果所有玩家都随机选择0-100，平均值约为50，目标值约为25。但理性玩家会意识到这一点，所以可能选择接近25的数字。然而如果大家都选25，平均值就是25，目标值就是12.5...\n\n这种迭代推理会收敛到0（纳什均衡）。但实际游戏中，玩家不会完全理性，第一轮通常会在某个中间值。\n\n作为Player 4，我需要在第一次尝试一个合理的估计。考虑到：\n1. 新手可能直接选50左右\n2. 有一定思考的玩家可能选25左右\n3. 深度思考的玩家可能选更低\n\n我猜测第一轮平均值可能在30-40之间，目标值在15-20之间。我选择18，这是一个保守的估计，既不太高（避免大家都理性选低值时我过高），也不太低（避免大家随机选时我过低）。",
        "Player 5": "这是第一轮游戏，没有任何历史信息可以参考。我需要分析这个博弈的结构：\n\n目标值 = 0.5 × (五人平均值) = 0.5 × (总和/5) = 总和/10\n\n如果所有玩家都随机选择0-100的数字，平均值大约是50，那么目标值大约是25。\n\n但这是一个典型的\"选美竞赛\"式博弈——玩家会推理其他玩家怎么选。理性推理链条：\n- 如果大家都选50，目标=25\n- 如果大家都意识到这一点而选25，目标=12.5\n- 继续推理下去会趋向于0\n\n然而在实际实验中，玩家通常不会完全理性地推到0。常见的均衡点在20-35之间。\n\n作为Player 5，我没有其他玩家的信息。稳妥策略是选择一个中等偏低的数字，既不过高也不过低。考虑到：\n- 完全随机的话目标≈25\n- 有一定理性的话目标会更低\n- 我需要猜测其他4个玩家的理性程度\n\n选择20是一个相对均衡的策略：低于 naive 的25，但不过度理性地选太低的数字。这样无论其他玩家偏理性还是偏随机，都有一定竞争力。"
      },
      "coherence_scores": {
        "Player 1": 0.9,
        "Player 2": 0.9,
        "Player 3": 0.9,
        "Player 4": 0.9,
        "Player 5": 0.9
      }
    },
    {
      "round": 2,
      "choices": {
        "Player 1": 12,
        "Player 2": 10,
        "Player 3": 12,
        "Player 4": 12,
        "Player 5": 13
      },
      "average": 11.8,
      "target": 5.9,
      "winner": "Player 2",
      "thoughts": {
        "Player 1": "第1轮结果分析：\n- 总和 = 22+22+25+18+20 = 107\n- 平均值 = 21.4\n- 目标值 = 0.5 × 21.4 = 10.7\n- 获胜者Player 4选择18，距离10.7差7.3\n\n有趣的是，所有玩家都选择了18-25之间的数字，没有人选择很低或很高的数字。这说明玩家们都有一定的理性，但可能只进行了一步或两步推理。\n\n我选择的22距离目标值10.7差11.3，表现不好。\n\n现在考虑第2轮：\n- 如果大家都基于第1轮结果调整，可能会向下调整\n- 第1轮目标值约10.7，但没人选那么低\n- 如果大家都选15左右，目标值会是7.5\n- 如果大家都意识到这点选7-8，目标值会是4左右\n\n但玩家不会完全理性收敛。观察第1轮分布：18,20,22,22,25，中位数是22。\n\n我需要预测其他人的调整：\n- 可能有人会向10-12靠拢（接近上轮目标值）\n- 可能有人会选15-18（轻微下调）\n- 可能有人保持20-25\n\n如果大家都往下调，比如平均到15，目标值是7.5。\n我选择12，这是一个介于\"上轮目标值10.7\"和\"理性预测7.5\"之间的折中，同时比大多数玩家的可能选择稍低，以争取在目标值偏低时获胜。",
        "Player 2": "第1轮结果分析：\n- 数字：22, 22, 25, 18, 20\n- 平均值 = 107/5 = 21.4\n- 目标 = 21.4 × 0.5 = 10.7\n- 获胜者Player 4选18，距离10.7差7.3\n\n有趣的现象：\n1. 所有玩家都选了中等偏低值（18-25），没有人选随机的高值\n2. 目标值10.7远低于大家的实际选择，说明大家都高估了\n3. 最接近目标的反而是最低的18\n\n这说明玩家们都有一定的理性，都在尝试预测并选择0.5倍平均值，但第一层推理（选25左右）就停止了，没有继续迭代下去。\n\n第2轮策略：\n- 如果大家都意识到目标会低于选择值，可能会进一步降低\n- 但如果大家都降低太多，目标也会相应变化\n- 理性均衡是0，但实际中玩家不会走那么极端\n\n观察：Player 4选18获胜，可能会保持或微调；其他玩家可能会降低。\n我预测本轮大家会选更低，平均值可能在15-20之间，目标约7.5-10。\n我应该选择8-12之间。选10是一个平衡的选择，既考虑了向下调整的趋势，又不过度激进。",
        "Player 3": "分析第1轮结果：\n- 数字：22, 22, 25, 18, 20\n- 总和：107\n- 平均值：21.4\n- 目标值：0.5 × 21.4 = 10.7\n- 获胜者：Player 4（选18，距离10.7差7.3）\n\n关键观察：\n1. 所有玩家都选择了相对理性的中低数字（18-25），没有人选极端高值\n2. 目标值10.7远低于所有人的选择，说明大家都高估了\n3. 最接近的是Player 4的18，但仍偏高\n\n这说明玩家们在第一层思维（目标≈25）附近，但实际目标更低。\n\n第2轮预测：\n- 玩家们会意识到目标比预期低，可能向下调整\n- 如果大家都选上一轮目标值附近（10-12），新目标≈5-6\n- 但玩家可能不会一步调整到位\n\n策略选择：\n- 保守：选10-12（基于上一轮实际目标）\n- 激进：选5-8（预测别人会下调）\n- 我选12，略低于上一轮实际目标10.7，但高于极端预测，平衡风险",
        "Player 4": "第1轮结果分析：\n- 五人数之和：22 + 22 + 25 + 18 + 20 = 107\n- 平均值：107 / 5 = 21.4\n- 目标值：0.5 × 21.4 = 10.7\n- 我的选择18，距离10.7差7.3，但其他玩家选择更高，所以我反而最接近获胜了\n\n有趣！其他玩家（1,2,3,5）都选择了20-25的范围，明显没有进行深度推理，或者他们认为别人会选50所以目标值是25。\n\n第2轮策略：\n- 其他玩家看到我赢了，可能会调整策略\n- 如果他们意识到目标值应该更低，可能会降低选择\n- 但如果他们只是模仿，可能继续选20-25\n\n假设其他玩家稍微理性化一点，可能选择15-22的范围。如果他们都选20左右，平均值20，目标值10。\n\n但我赢了上一轮，其他玩家可能注意到我的18是最低的，可能会向下调整。如果大家都往低处走，目标值会更低。\n\n我猜测这一轮平均值可能在15-18之间，目标值在7.5-9之间。我选择12，比上一轮低，但不过低（防止大家还是不够理性）。",
        "Player 5": "上一轮结果分析：\n- 数字：22, 22, 25, 18, 20（我）\n- 总和 = 107，平均值 = 21.4，目标 = 10.7\n- Player 4 选18获胜，最接近10.7\n\n关键发现：\n1. 所有玩家都选了18-25的偏低数字，说明大家都做了一定理性推理（没有选50附近的naive数字）\n2. 但目标值10.7比所有人的选择都低！说明大家还是\"不够理性\"——理性推理应该推到更低\n3. Player 4选18最接近，但即使18也远高于目标10.7\n\n博弈论分析：\n- 如果所有人继续类似的理性程度（选15-25范围），平均值约20，目标约10\n- 但如果有人意识到这一点，应该选10左右\n- 进一步：如果大家都意识到要往10靠，目标会更低...\n\n策略考量：\n- 上一轮大家集中在18-25，这次可能会向下调整\n- 如果我假设大家会降到15-20范围，平均值约17，目标约8.5\n- 但如果我过度推理选太低（如5），而其他人只降到15，目标7.5，我选5反而离得远\n\n稳妥策略：比上一轮最低值18再低一些，但不要过度。选12-15范围。我选择13，既体现向下调整的趋势，又不过度理性。"
      },
      "coherence_scores": {
        "Player 1": 0.9,
        "Player 2": 0.9,
        "Player 3": 0.9,
        "Player 4": 0.9,
        "Player 5": 0.9
      }
    },
    {
      "round": 3,
      "choices": {
        "Player 1": 4,
        "Player 2": 4,
        "Player 3": 6,
        "Player 4": 6,
        "Player 5": 6
      },
      "average": 5.2,
      "target": 2.6,
      "winner": "Player 1",
      "thoughts": {
        "Player 1": "第2轮结果分析：\n- 总和 = 12+10+12+12+13 = 59\n- 平均值 = 11.8\n- 目标值 = 0.5 × 11.8 = 5.9\n- 获胜者Player 2选择10，距离5.9差4.1\n\n我选择的12距离5.9差6.1，表现不够好。\n\n关键观察：\n1. 玩家们明显向下调整了（从18-25降到10-13）\n2. 但目标值5.9比所有人的选择都低！说明大家调整得还不够\n3. Player 2选择10获胜，是所有人中最低的\n\n这说明收敛过程正在进行，但玩家们的调整有滞后性。大家都在追逐上一轮的目标值，但目标值本身在快速下降。\n\n预测第3轮：\n- 看到目标值只有5.9，玩家们可能会进一步下调\n- 如果大家都选6-8，目标值会是3-4\n- 如果大家都理性地选3-4，目标值会是1.5-2\n\n但收敛不会无限进行，玩家会意识到过度下调的风险。\n\n我需要预判其他人的选择：\n- 可能有人选6-7（接近上轮目标值）\n- 可能有人选8-10（保守下调）\n- 可能有人选3-5（激进下调）\n\n如果平均选择约7，目标值是3.5。\n我选择5，这是一个激进但不过度的选择：比上轮目标值5.9更低，但不像1-2那样极端。如果其他人选6-8，目标值约3.5，我距离1.5；如果我选5，距离2.5。实际上让我重新计算：如果平均7，目标3.5，选5差1.5，选4差0.5，选3差0.5。\n\n我选择4，在激进和保守之间取得平衡，同时预判目标值会降到3-4区间。",
        "Player 2": "第2轮结果分析：\n- 数字：12, 10, 12, 12, 13\n- 平均值 = 59/5 = 11.8\n- 目标 = 11.8 × 0.5 = 5.9\n- 我选10获胜，距离5.9差4.1（其他玩家距离更远）\n\n关键观察：\n1. 所有玩家都显著降低了选择（从18-25降到10-13）\n2. 但我选10仍然偏高，目标实际只有5.9\n3. 大家同步降低，但降低幅度不够\n\n这说明玩家们在进行「迭代推理」：\n- 第1轮：选~22（认为别人选~44，实际别人也选~22）\n- 第2轮：选~12（认为别人会降，实际别人也选~12）\n\n第3轮预测：\n- 如果大家都意识到目标5.9低于选择，会继续降低\n- 可能降到6-8范围\n- 但如果大家都这么想，目标会进一步降到3-4\n\n我需要预判这个迭代深度：\n- 保守估计：大家选6-8，目标3-4，我应该选3-5\n- 激进估计：大家选3-5，目标1.5-2.5\n\n考虑到实际博弈中迭代不会无限进行，且第2轮已显示同步行为，我预测本轮平均值约7-8，目标约3.5-4。\n我选择4，这是一个既有前瞻性又不过度激进的策略。",
        "Player 3": "分析第2轮结果：\n- 数字：12, 10, 12, 12, 13\n- 总和：59\n- 平均值：11.8\n- 目标值：0.5 × 11.8 = 5.9\n- 获胜者：Player 2（选10，距离5.9差4.1）\n\n关键观察：\n1. 所有玩家都大幅下调到10-13区间，非常集中\n2. 但实际目标值5.9远低于所有人的选择\n3. 又一次集体高估！这说明收敛速度比预期慢\n4. Player 2选10获胜，虽然仍偏高，但相对最接近\n\n模式识别：\n- 第1轮：目标≈10.7，大家选18-25\n- 第2轮：目标≈5.9，大家选10-13\n- 两轮都是实际目标 ≈ 大家选择的0.5倍左右\n\n第3轮预测：\n- 玩家会继续下调，可能集中到5-8区间\n- 如果大家都选5-8，平均值6.5，目标≈3.25\n- 但需要判断收敛速度\n\n策略选择：\n- 如果选6-7：假设别人选5-8，可能偏高\n- 如果选3-4：假设别人充分理性，风险较大\n- 我选6，略保守，考虑到玩家可能不会一步调到理论最优",
        "Player 4": "第2轮结果分析：\n- 五人数之和：12 + 10 + 12 + 12 + 13 = 59\n- 平均值：59 / 5 = 11.8\n- 目标值：0.5 × 11.8 = 5.9\n- Player 2选择10，距离5.9差4.1，获胜\n\n关键观察：\n1. 所有玩家都大幅降低了选择（从20-25降到10-13）！这说明大家都在学习和适应\n2. 我的12虽然比上一轮低，但还是太高了，目标值只有5.9\n3. Player 2的10最接近，但即使10也偏高\n\n第3轮策略：\n- 现在大家意识到目标值应该更低，可能会继续降低\n- 如果大家都选6-10，平均值8，目标值4\n- 如果大家都更激进，可能选3-7，平均值5，目标值2.5\n\n这是一个收敛过程，向纳什均衡0靠近。但玩家不会一步到位选0。\n\n我需要预判其他人的调整幅度。看到目标值只有5.9，大家可能会选4-8的范围。\n如果选5-8，平均值6.5，目标值3.25。\n\n我选择6，这是一个中等偏保守的估计，既反映了向下的趋势，又不过度激进（防止有人还没反应过来）。",
        "Player 5": "上一轮结果分析：\n- 数字：12, 10, 12, 12, 13（我）\n- 总和 = 59，平均值 = 11.8，目标 = 5.9\n- Player 2 选10获胜，最接近5.9\n\n关键发现：\n1. 大家显著向下调整！从18-25降到了10-13\n2. 但目标5.9仍然比所有人的选择都低\n3. 我选13是最高值，离目标最远，表现最差\n4. Player 2选10最接近，但10仍比5.9高\n\n动态分析：\n- 两轮下来，目标值从10.7降到5.9，持续下降\n- 玩家们在学习，但学习速度不够快，始终高于目标\n- 如果这种趋势继续，大家会进一步下调\n\n预测本轮：\n- 如果大家都意识到目标约6，可能选6-10范围\n- 但如果大家都选7-8，平均值7.5，目标3.75\n- 如果过度内卷，可能推到更低\n\n策略选择：\n- 保守：选6-7，假设大家降到8-10\n- 激进：选3-4，假设大家充分理性\n- 上一轮大家从18降到10（降幅约45%），如果同比例降，可能到5-6\n\n我选择6：比上一轮目标5.9略高，假设大家会接近但未完全达到理性均衡。这样既跟上下降趋势，又不过度超前。"
      },
      "coherence_scores": {
        "Player 1": 0.9,
        "Player 2": 0.9,
        "Player 3": 0.9,
        "Player 4": 0.9,
        "Player 5": 0.9
      }
    },
    {
      "round": 4,
      "choices": {
        "Player 1": 2,
        "Player 2": 2,
        "Player 3": 3,
        "Player 4": 3,
        "Player 5": 2
      },
      "average": 2.4,
      "target": 1.2,
      "winner": "Player 1",
      "thoughts": {
        "Player 1": "第3轮结果分析：\n- 总和 = 4+4+6+6+6 = 26\n- 平均值 = 5.2\n- 目标值 = 0.5 × 5.2 = 2.6\n- 获胜者：Player 1（我！）选择4，距离2.6差1.4\n\n我赢了！但我的选择4其实比目标值2.6高，只是其他人选得更高。这说明我预判对了方向（向下调整），但调整幅度还不够激进。\n\n关键观察：\n1. 我和Player 2都选了4，其他人选6\n2. 目标值2.6比所有人的选择都低，再次证明收敛滞后\n3. 玩家们正在学习，但学习速度不同\n\n预测第4轮：\n- 看到目标值只有2.6，玩家们会进一步下调\n- 如果大家都选2-3，目标值会是1-1.5\n- 但玩家不会无限下调，可能有人在3-4止步\n\n我需要预判新的均衡点：\n- 保守派：可能选3-4（认为不会降太多）\n- 激进派：可能选1-2（追逐理论均衡0）\n- 中间派：可能选2-3\n\n如果平均选择约2.5，目标值是1.25。\n\n但我作为上轮获胜者，有信息优势。其他人看到目标值2.6，可能：\n- Player 2（也选4）可能选3\n- 选6的三人可能大幅下调到2-3\n\n如果大家都选2-3，目标值1-1.5。我选择2，预判目标值在1.5-2.5之间，2是一个相对安全且可能获胜的选择。如果目标值偏低（1.5），我差0.5；如果偏高（2.5），我也差0.5。",
        "Player 2": "第3轮结果分析：\n- 数字：4, 4, 6, 6, 6\n- 平均值 = 26/5 = 5.2\n- 目标 = 5.2 × 0.5 = 2.6\n- Player 1选4获胜，距离2.6差1.4\n\n关键观察：\n1. 玩家分成两派：4和6，我选4与Player 1并列最低\n2. 目标2.6远低于所有选择，说明大家还是高估了\n3. 迭代继续：从~12降到~5，目标降到~2.6\n\n动态分析：\n- 第1轮：选~22，目标~10.7\n- 第2轮：选~12，目标~5.9  \n- 第3轮：选~5.2，目标~2.6\n\n明显的收敛趋势！每次目标大约是选择的0.5倍。\n\n第4轮预测：\n- 如果大家都理性，会选~2.6，目标~1.3\n- 但Player 3/4/5选6，可能反应较慢或策略不同\n- Player 1选4，和我一样，是敏锐的竞争者\n\n策略考量：\n- 如果大家都降到2-3，目标1-1.5，我应该选1-2\n- 但如果有玩家仍选5-6（惯性），目标会抬高到1.5-2\n- Player 1是我的直接对手，他可能选2-3\n\n我选择2，这是一个既能应对快速收敛趋势，又不过度激进到0或1的策略。如果大家都理性降到2-3，目标1-1.5，我距离1.5差0.5；如果有人滞后选4-6，目标可能到2，我正好命中。",
        "Player 3": "分析第3轮结果：\n- 数字：4, 4, 6, 6, 6\n- 总和：26\n- 平均值：5.2\n- 目标值：0.5 × 5.2 = 2.6\n- 获胜者：Player 1（选4，距离2.6差1.4）\n\n关键观察：\n1. 玩家分化：Player 1和2选4，Player 3、4、5选6\n2. 实际目标2.6，最接近的是4（仍偏高）\n3. 又一次集体高估，但差距缩小了\n4. 我选6，距离2.6差3.4，表现较差\n\n模式分析：\n- 第1轮目标≈10.7，第2轮目标≈5.9，第3轮目标≈2.6\n- 目标值在快速下降，接近0\n- 玩家选择：25→12→6→4，也在收敛\n\n第4轮预测：\n- 玩家会继续下调，可能选2-4\n- 如果大家都选2-4，平均值3，目标≈1.5\n- 如果有人激进选0-1，目标会更低\n\n策略困境：\n- 选太低（0-1）：如果别人选3-4，平均值高，目标≈2，我输\n- 选中等（2-3）：平衡选择\n- 选偏高（4+）：可能再次高估\n\n考虑到玩家收敛速度，我选3。假设别人选2-4，平均值3，目标1.5，我距离1.5差1.5，有竞争力。",
        "Player 4": "第3轮结果分析：\n- 五人数之和：4 + 4 + 6 + 6 + 6 = 26\n- 平均值：26 / 5 = 5.2\n- 目标值：0.5 × 5.2 = 2.6\n- Player 1和2选择4，距离2.6差1.4，获胜（并列）\n\n关键观察：\n1. 继续向低收敛！Player 1和2已经降到4，我、3、5选6\n2. 目标值只有2.6，说明即使4还是偏高了\n3. 现在有两名玩家（1、2）领先，他们可能会继续降低或保持低位\n\n第4轮策略：\n- 收敛趋势明显，目标值会越来越低\n- 如果大家都意识到目标值约2.6，可能选择2-4\n- 如果选3-5，平均值4，目标值2\n- Player 1和2赢了，可能继续选低或保持4\n- 其他玩家（3、5和我）看到4获胜，可能也会降低\n\n预测：这一轮选择可能在2-5之间，平均值3-4，目标值1.5-2\n\n我需要比上一轮更低，但不能过低（防止有人还没跟上）。选择3是一个合理的估计，如果平均值是6（有人滞后），目标值3；如果平均值更低，目标值也更低。3比4更接近可能的低位目标值。",
        "Player 5": "上一轮结果分析：\n- 数字：4, 4, 6, 6, 6（我）\n- 总和 = 26，平均值 = 5.2，目标 = 2.6\n- Player 1 和 Player 2 选4获胜，最接近2.6\n\n关键发现：\n1. 目标值降到2.6，非常低！\n2. 我选6，离目标较远，表现不好\n3. Player 1和2选4，最接近2.6\n4. 数字分布：4（2人）, 6（3人），出现明显分层\n\n趋势分析：\n- 目标值：10.7 → 5.9 → 2.6，持续快速下降\n- 玩家选择：18-25 → 10-13 → 4-6，降幅加大\n- 但即使选4，仍高于目标2.6\n\n预测本轮：\n- 大家会意识到目标在2-3附近\n- 如果都理性选择2-3，平均值2.5，目标1.25\n- 如果选1-2，平均值1.5，目标0.75\n- 继续推到极限会趋向0\n\n博弈困境：\n- 选太低（0-1）：如果其他人没这么激进，目标较高，我会输\n- 选中等（2-3）：平衡策略\n- 选较高（4+）：可能重复上一轮错误\n\n观察Player 1和2：他们连续两轮表现好（第2轮10，第3轮4），说明他们调整更快。\n\n策略：选择2。理由：\n- 上一轮目标2.6，选4获胜\n- 如果同比例下降，目标约1.3\n- 选2比目标略高，假设大家不会完全推到0\n- 同时跟上领先者(Player 1,2)的快速下调节奏"
      },
      "coherence_scores": {
        "Player 1": 0.9,
        "Player 2": 0.9,
        "Player 3": 0.9,
        "Player 4": 0.9,
        "Player 5": 0.9
      }
    },
    {
      "round": 5,
      "choices": {
        "Player 1": 1,
        "Player 2": 1,
        "Player 3": 1,
        "Player 4": 1,
        "Player 5": 1
      },
      "average": 1.0,
      "target": 0.5,
      "winner": "Player 1",
      "thoughts": {
        "Player 1": "第4轮结果分析：\n- 总和 = 2+2+3+3+2 = 12\n- 平均值 = 2.4\n- 目标值 = 0.5 × 2.4 = 1.2\n- 获胜者：Player 1（我！）选择2，距离1.2差0.8\n\n再次获胜！我和Player 2、Player 5都选了2，其他人选3。目标值1.2再次低于所有人的选择，收敛过程仍在继续。\n\n关键观察：\n1. 选择高度集中在2-3，显示玩家们已经相当理性\n2. 目标值1.2表明还需要进一步下调\n3. 但下调空间有限，已经接近0\n\n预测第5轮：\n- 看到目标值1.2，玩家们会意识到需要选1或更低\n- 但选0或1的风险：如果其他人没跟上，目标值可能偏高\n- 可能的分布：0, 1, 1, 2, 2 或类似\n\n博弈论均衡是0，但实际中玩家会停在某个正数。\n\n我需要预判：\n- 保守派：可能选1（认为目标值1-2）\n- 激进派：可能选0（追逐均衡）\n- 犹豫派：可能选2（没跟上调整）\n\n如果平均选择约1，目标值是0.5。\n\n我选择1：\n- 如果大家都选1，目标值0.5，我差0.5\n- 如果平均1.5，目标值0.75，我差0.25\n- 如果有人选0，目标值更低，1仍可能接近\n\n选0的风险：如果其他人选1-2，目标值0.5-1，我选0差0.5-1，不如选1。\n\n选1是平衡风险与收益的最优选择。",
        "Player 2": "第4轮结果分析：\n- 数字：2, 2, 3, 3, 2\n- 平均值 = 12/5 = 2.4\n- 目标 = 2.4 × 0.5 = 1.2\n- Player 1选2获胜，距离1.2差0.8\n\n关键观察：\n1. 选择分布：2,2,2,3,3 —— 高度集中在2-3\n2. 目标1.2远低于选择，大家继续高估\n3. 我和Player 1、Player 5都选2，Player 1获胜（可能随机或规则）\n\n收敛趋势加速：\n- 第1轮：~22 → 目标~11\n- 第2轮：~12 → 目标~6\n- 第3轮：~5.2 → 目标~2.6\n- 第4轮：~2.4 → 目标~1.2\n\n第5轮预测：\n- 理性推断：大家会选~1.2，目标~0.6\n- 实际行为：可能选0,1,2\n- Player 1是强劲对手，可能选0或1\n\n博弈困境：\n- 如果大家都选0-1，目标0-0.5，选0最好\n- 但如果有人选2-3（惯性），目标抬高，选0就输了\n\n观察Player 3/4：从6→3，下降较慢，可能仍有惯性\n\n我选择1，这是一个平衡策略：\n- 比上一轮目标1.2略低，体现学习\n- 不过度激进到0，防止有人选2-3拉高目标\n- 如果大家都理性选0-1，目标0-0.5，我距离0.5差0.5\n- 如果有人选2，目标0.7-0.8，我距离较近",
        "Player 3": "分析第4轮结果：\n- 数字：2, 2, 3, 3, 2\n- 总和：12\n- 平均值：2.4\n- 目标值：0.5 × 2.4 = 1.2\n- 获胜者：Player 1（选2，距离1.2差0.8）\n\n关键观察：\n1. 玩家高度集中：2或3，非常理性\n2. 目标值1.2，最接近的是2（仍略高）\n3. 我选3，距离1.2差1.8，表现一般\n4. 连续4轮目标值都低于所有人的选择\n\n模式分析：\n- 目标序列：10.7 → 5.9 → 2.6 → 1.2，快速趋近于0\n- 选择序列：22/25 → 12/13 → 4/6 → 2/3，也在收敛\n- 但每次目标都略低于最低选择\n\n第5轮预测：\n- 玩家会继续下调，可能选0-2\n- 如果大家都选0-2，平均值1，目标≈0.5\n- 如果选0的人变多，目标接近0\n\n策略选择：\n- 选0：激进，但如果别人选1-2，平均值高，目标≈1，我输\n- 选1：平衡，假设别人选0-2，平均值1，目标0.5，我距离0.5差0.5\n- 选2：保守，可能再次高估\n\n考虑到玩家可能不会一步到0，我选1。这是理论最优附近的平衡选择。",
        "Player 4": "第4轮结果分析：\n- 五人数之和：2 + 2 + 3 + 3 + 2 = 12\n- 平均值：12 / 5 = 2.4\n- 目标值：0.5 × 2.4 = 1.2\n- Player 1、2、5选择2，距离1.2差0.8，获胜（并列）\n\n关键观察：\n1. 极度收敛！三名玩家选2，两名选3\n2. 目标值只有1.2，说明2还是偏高\n3. 现在3名玩家领先，他们可能继续降低\n\n第5轮策略：\n- 趋势是向0收敛，但速度在减缓\n- 如果大家都选2，平均值2，目标值1\n- 如果三名获胜者降到1，其他人选2，平均值1.4，目标值0.7\n- 如果大家都降到1，平均值1，目标值0.5\n\n关键问题：玩家会降到0或1吗？还是停留在2？\n- 选0是纳什均衡，但风险大（如果别人选高，目标值高，0就输了）\n- 选1是安全且进取的选择\n- 选2可能过于保守\n\n预测：这一轮可能在0-2之间，平均值1-1.5，目标值0.5-0.75\n\n我选择1。如果大家都理性，目标值约0.5-1，1最接近；如果有人还选2，目标值约1.2，1也最接近。1比2更接近预期的低位目标值，又比0安全（防止有人滞后选2-3）。",
        "Player 5": "上一轮结果分析：\n- 数字：2, 2, 3, 3, 2（我）\n- 总和 = 12，平均值 = 2.4，目标 = 1.2\n- Player 1, 2, 5（我）选2获胜，最接近1.2\n\n关键发现：\n1. 我选2，与Player 1, 2并列获胜！\n2. 目标1.2，选2仍比目标高，但已经是整数中最接近的（选1的话差0.8，选2差0.8，相同）\n3. 数字分布：2（3人）, 3（2人），非常集中\n4. 目标值持续下降：10.7 → 5.9 → 2.6 → 1.2\n\n趋势分析：\n- 降幅趋缓：从10.7到5.9（降4.8），5.9到2.6（降3.3），2.6到1.2（降1.4）\n- 玩家选择已接近极限，难以再大幅下调\n- 当前选择2-3，目标1.2，差距已经很小\n\n预测本轮：\n- 如果大家都意识到目标约1，可能选0-2\n- 如果选0,1,1,1,2，平均值1，目标0.5\n- 如果选0,0,1,1,2，平均值0.8，目标0.4\n- 极限情况趋向0\n\n博弈考量：\n- Player 1和2连续多轮领先，他们很可能继续下调到0或1\n- 如果我选2，而他们都选0或1，目标变低，我输\n- 如果我选0，而大家选1-2，目标约1，我输\n- 选1是平衡：无论大家选0,1,2，都有竞争力\n\n策略：选择1。理由：\n- 上一轮目标1.2，选2获胜但已临界\n- 领先者(Player 1,2)可能继续下调到0或1\n- 选1比2更优：若目标<1.5，1比2更接近\n- 避免选0的极端风险，同时跟上下降趋势"
      },
      "coherence_scores": {
        "Player 1": 0.9,
        "Player 2": 0.9,
        "Player 3": 0.9,
        "Player 4": 0.9,
        "Player 5": 0.9
      }
    }
  ],
  "agents": [
    {
      "name": "Player 1",
      "messages": [
        {
          "role": "user",
          "content": "第 1 轮：请给出你的选择（JSON 格式：{\"thought\": \"...\", \"number\": 整数}）。"
        },
        {
          "role": "assistant",
          "content": "```json\n{\"thought\": \"这是第一轮游戏，没有任何历史信息可以参考。我需要分析这个博弈的结构：\\n\\n目标值 = 0.5 × (五人平均值) = 0.5 × (总和/5) = 总和/10\\n\\n如果所有玩家都选择相同的数字 x，那么目标值 = (5x)/10 = 0.5x，所以最优选择应该是 0.5x。但如果大家都理性地选择 0.5x，那么新的目标值又变成 0.25x，依此类推，这会导致向0收敛的迭代过程。\\n\\n在经典的\\\"选平均数的2/3\\\"博弈中，理性推理会导致选择接近0。但这里是\\\"选平均数的1/2\\\"，收敛速度更快。\\n\\n然而，现实中玩家不会完全理性：\\n1. 有些玩家可能不理解规则，随机选择\\n2. 有些玩家可能选择中间值50\\n3. 有些玩家可能进行多步推理\\n\\n作为第一轮，我需要做一个平衡的选择：\\n- 如果大家都选50，目标值是25\\n- 如果大家都理性地选25，目标值是12.5\\n- 如果进行两步推理，选12.5，目标值是6.25\\n\\n考虑到混合策略，选择15-25之间比较安全。我选择22，这是一个介于 naive (50) 和理性推理结果之间的值，既能应对部分理性玩家，也能在其他人选择较高数字时有竞争力。\", \"number\": 22}\n```"
        },
        {
          "role": "user",
          "content": "上一轮（第 1 轮）结果：\nPlayer 1: 22\nPlayer 2: 22\nPlayer 3: 25\nPlayer 4: 18\nPlayer 5: 20\n当轮获胜者：Player 4。\n\n本轮是第 2 轮。请根据以上信息给出你的选择。"
        },
        {
          "role": "assistant",
          "content": "```json\n{\"thought\": \"第1轮结果分析：\\n- 总和 = 22+22+25+18+20 = 107\\n- 平均值 = 21.4\\n- 目标值 = 0.5 × 21.4 = 10.7\\n- 获胜者Player 4选择18，距离10.7差7.3\\n\\n有趣的是，所有玩家都选择了18-25之间的数字，没有人选择很低或很高的数字。这说明玩家们都有一定的理性，但可能只进行了一步或两步推理。\\n\\n我选择的22距离目标值10.7差11.3，表现不好。\\n\\n现在考虑第2轮：\\n- 如果大家都基于第1轮结果调整，可能会向下调整\\n- 第1轮目标值约10.7，但没人选那么低\\n- 如果大家都选15左右，目标值会是7.5\\n- 如果大家都意识到这点选7-8，目标值会是4左右\\n\\n但玩家不会完全理性收敛。观察第1轮分布：18,20,22,22,25，中位数是22。\\n\\n我需要预测其他人的调整：\\n- 可能有人会向10-12靠拢（接近上轮目标值）\\n- 可能有人会选15-18（轻微下调）\\n- 可能有人保持20-25\\n\\n如果大家都往下调，比如平均到15，目标值是7.5。\\n我选择12，这是一个介于\\\"上轮目标值10.7\\\"和\\\"理性预测7.5\\\"之间的折中，同时比大多数玩家的可能选择稍低，以争取在目标值偏低时获胜。\", \"number\": 12}\n```"
        },
        {
          "role": "user",
          "content": "上一轮（第 2 轮）结果：\nPlayer 1: 12\nPlayer 2: 10\nPlayer 3: 12\nPlayer 4: 12\nPlayer 5: 13\n当轮获胜者：Player 2。\n\n本轮是第 3 轮。请根据以上信息给出你的选择。"
        },
        {
          "role": "assistant",
          "content": "```json\n{\"thought\": \"第2轮结果分析：\\n- 总和 = 12+10+12+12+13 = 59\\n- 平均值 = 11.8\\n- 目标值 = 0.5 × 11.8 = 5.9\\n- 获胜者Player 2选择10，距离5.9差4.1\\n\\n我选择的12距离5.9差6.1，表现不够好。\\n\\n关键观察：\\n1. 玩家们明显向下调整了（从18-25降到10-13）\\n2. 但目标值5.9比所有人的选择都低！说明大家调整得还不够\\n3. Player 2选择10获胜，是所有人中最低的\\n\\n这说明收敛过程正在进行，但玩家们的调整有滞后性。大家都在追逐上一轮的目标值，但目标值本身在快速下降。\\n\\n预测第3轮：\\n- 看到目标值只有5.9，玩家们可能会进一步下调\\n- 如果大家都选6-8，目标值会是3-4\\n- 如果大家都理性地选3-4，目标值会是1.5-2\\n\\n但收敛不会无限进行，玩家会意识到过度下调的风险。\\n\\n我需要预判其他人的选择：\\n- 可能有人选6-7（接近上轮目标值）\\n- 可能有人选8-10（保守下调）\\n- 可能有人选3-5（激进下调）\\n\\n如果平均选择约7，目标值是3.5。\\n我选择5，这是一个激进但不过度的选择：比上轮目标值5.9更低，但不像1-2那样极端。如果其他人选6-8，目标值约3.5，我距离1.5；如果我选5，距离2.5。实际上让我重新计算：如果平均7，目标3.5，选5差1.5，选4差0.5，选3差0.5。\\n\\n我选择4，在激进和保守之间取得平衡，同时预判目标值会降到3-4区间。\", \"number\": 4}\n```"
        },
        {
          "role": "user",
          "content": "上一轮（第 3 轮）结果：\nPlayer 1: 4\nPlayer 2: 4\nPlayer 3: 6\nPlayer 4: 6\nPlayer 5: 6\n当轮获胜者：Player 1。\n\n本轮是第 4 轮。请根据以上信息给出你的选择。"
        },
        {
          "role": "assistant",
          "content": " ```json\n{\"thought\": \"第3轮结果分析：\\n- 总和 = 4+4+6+6+6 = 26\\n- 平均值 = 5.2\\n- 目标值 = 0.5 × 5.2 = 2.6\\n- 获胜者：Player 1（我！）选择4，距离2.6差1.4\\n\\n我赢了！但我的选择4其实比目标值2.6高，只是其他人选得更高。这说明我预判对了方向（向下调整），但调整幅度还不够激进。\\n\\n关键观察：\\n1. 我和Player 2都选了4，其他人选6\\n2. 目标值2.6比所有人的选择都低，再次证明收敛滞后\\n3. 玩家们正在学习，但学习速度不同\\n\\n预测第4轮：\\n- 看到目标值只有2.6，玩家们会进一步下调\\n- 如果大家都选2-3，目标值会是1-1.5\\n- 但玩家不会无限下调，可能有人在3-4止步\\n\\n我需要预判新的均衡点：\\n- 保守派：可能选3-4（认为不会降太多）\\n- 激进派：可能选1-2（追逐理论均衡0）\\n- 中间派：可能选2-3\\n\\n如果平均选择约2.5，目标值是1.25。\\n\\n但我作为上轮获胜者，有信息优势。其他人看到目标值2.6，可能：\\n- Player 2（也选4）可能选3\\n- 选6的三人可能大幅下调到2-3\\n\\n如果大家都选2-3，目标值1-1.5。我选择2，预判目标值在1.5-2.5之间，2是一个相对安全且可能获胜的选择。如果目标值偏低（1.5），我差0.5；如果偏高（2.5），我也差0.5。\", \"number\": 2}\n```"
        },
        {
          "role": "user",
          "content": "上一轮（第 4 轮）结果：\nPlayer 1: 2\nPlayer 2: 2\nPlayer 3: 3\nPlayer 4: 3\nPlayer 5: 2\n当轮获胜者：Player 1。\n\n本轮是第 5 轮。请根据以上信息给出你的选择。"
        },
        {
          "role": "assistant",
          "content": " ```json\n{\"thought\": \"第4轮结果分析：\\n- 总和 = 2+2+3+3+2 = 12\\n- 平均值 = 2.4\\n- 目标值 = 0.5 × 2.4 = 1.2\\n- 获胜者：Player 1（我！）选择2，距离1.2差0.8\\n\\n再次获胜！我和Player 2、Player 5都选了2，其他人选3。目标值1.2再次低于所有人的选择，收敛过程仍在继续。\\n\\n关键观察：\\n1. 选择高度集中在2-3，显示玩家们已经相当理性\\n2. 目标值1.2表明还需要进一步下调\\n3. 但下调空间有限，已经接近0\\n\\n预测第5轮：\\n- 看到目标值1.2，玩家们会意识到需要选1或更低\\n- 但选0或1的风险：如果其他人没跟上，目标值可能偏高\\n- 可能的分布：0, 1, 1, 2, 2 或类似\\n\\n博弈论均衡是0，但实际中玩家会停在某个正数。\\n\\n我需要预判：\\n- 保守派：可能选1（认为目标值1-2）\\n- 激进派：可能选0（追逐均衡）\\n- 犹豫派：可能选2（没跟上调整）\\n\\n如果平均选择约1，目标值是0.5。\\n\\n我选择1：\\n- 如果大家都选1，目标值0.5，我差0.5\\n- 如果平均1.5，目标值0.75，我差0.25\\n- 如果有人选0，目标值更低，1仍可能接近\\n\\n选0的风险：如果其他人选1-2，目标值0.5-1，我选0差0.5-1，不如选1。\\n\\n选1是平衡风险与收益的最优选择。\", \"number\": 1}\n```"
        }
      ]
    },
    {
      "name": "Player 2",
      "messages": [
        {
          "role": "user",
          "content": "第 1 轮：请给出你的选择（JSON 格式：{\"thought\": \"...\", \"number\": 整数}）。"
        },
        {
          "role": "assistant",
          "content": " ```json\n{\"thought\": \"这是第1轮，我没有历史信息可以参考。让我分析这个游戏：\\n\\n目标 = 0.5 × (五人数字之和 / 5) = (五人数字之和) / 10\\n\\n如果所有玩家都随机选择0-100，平均值约50，那么目标约25。\\n\\n但这涉及到博弈论中的「选美比赛」问题：每个玩家都想预测别人的选择，然后选择那个预测值的0.5倍。\\n\\n- 如果大家都理性，会想：别人平均选50，我应该选25\\n- 但如果别人也想到了这一点，他们会选25，那么目标就是12.5\\n- 继续迭代：25→12.5→6.25→3.125...\\n\\n理论上理性玩家的均衡趋近于0。但在实际游戏中，并非所有玩家都完全理性。\\n\\n作为第一轮，我需要平衡：\\n- 如果选太高（如50），别人选低的话我会输\\n- 如果选太低（如0），别人选中等值的话我也会输\\n\\n一个合理的策略是选择一个中等偏低的值，比如20-30之间，既考虑了部分理性玩家会选低值，也考虑了可能有非理性的高值选择。我选择22，这是一个在第一轮相对安全的中间策略。\", \"number\": 22}\n```"
        },
        {
          "role": "user",
          "content": "上一轮（第 1 轮）结果：\nPlayer 1: 22\nPlayer 2: 22\nPlayer 3: 25\nPlayer 4: 18\nPlayer 5: 20\n当轮获胜者：Player 4。\n\n本轮是第 2 轮。请根据以上信息给出你的选择。"
        },
        {
          "role": "assistant",
          "content": "```json\n{\"thought\": \"第1轮结果分析：\\n- 数字：22, 22, 25, 18, 20\\n- 平均值 = 107/5 = 21.4\\n- 目标 = 21.4 × 0.5 = 10.7\\n- 获胜者Player 4选18，距离10.7差7.3\\n\\n有趣的现象：\\n1. 所有玩家都选了中等偏低值（18-25），没有人选随机的高值\\n2. 目标值10.7远低于大家的实际选择，说明大家都高估了\\n3. 最接近目标的反而是最低的18\\n\\n这说明玩家们都有一定的理性，都在尝试预测并选择0.5倍平均值，但第一层推理（选25左右）就停止了，没有继续迭代下去。\\n\\n第2轮策略：\\n- 如果大家都意识到目标会低于选择值，可能会进一步降低\\n- 但如果大家都降低太多，目标也会相应变化\\n- 理性均衡是0，但实际中玩家不会走那么极端\\n\\n观察：Player 4选18获胜，可能会保持或微调；其他玩家可能会降低。\\n我预测本轮大家会选更低，平均值可能在15-20之间，目标约7.5-10。\\n我应该选择8-12之间。选10是一个平衡的选择，既考虑了向下调整的趋势，又不过度激进。\", \"number\": 10}\n```"
        },
        {
          "role": "user",
          "content": "上一轮（第 2 轮）结果：\nPlayer 1: 12\nPlayer 2: 10\nPlayer 3: 12\nPlayer 4: 12\nPlayer 5: 13\n当轮获胜者：Player 2。\n\n本轮是第 3 轮。请根据以上信息给出你的选择。"
        },
        {
          "role": "assistant",
          "content": "```json\n{\"thought\": \"第2轮结果分析：\\n- 数字：12, 10, 12, 12, 13\\n- 平均值 = 59/5 = 11.8\\n- 目标 = 11.8 × 0.5 = 5.9\\n- 我选10获胜，距离5.9差4.1（其他玩家距离更远）\\n\\n关键观察：\\n1. 所有玩家都显著降低了选择（从18-25降到10-13）\\n2. 但我选10仍然偏高，目标实际只有5.9\\n3. 大家同步降低，但降低幅度不够\\n\\n这说明玩家们在进行「迭代推理」：\\n- 第1轮：选~22（认为别人选~44，实际别人也选~22）\\n- 第2轮：选~12（认为别人会降，实际别人也选~12）\\n\\n第3轮预测：\\n- 如果大家都意识到目标5.9低于选择，会继续降低\\n- 可能降到6-8范围\\n- 但如果大家都这么想，目标会进一步降到3-4\\n\\n我需要预判这个迭代深度：\\n- 保守估计：大家选6-8，目标3-4，我应该选3-5\\n- 激进估计：大家选3-5，目标1.5-2.5\\n\\n考虑到实际博弈中迭代不会无限进行，且第2轮已显示同步行为，我预测本轮平均值约7-8，目标约3.5-4。\\n我选择4，这是一个既有前瞻性又不过度激进的策略。\", \"number\": 4}\n```"
        },
        {
          "role": "user",
          "content": "上一轮（第 3 轮）结果：\nPlayer 1: 4\nPlayer 2: 4\nPlayer 3: 6\nPlayer 4: 6\nPlayer 5: 6\n当轮获胜者：Player 1。\n\n本轮是第 4 轮。请根据以上信息给出你的选择。"
        },
        {
          "role": "assistant",
          "content": "```json\n{\"thought\": \"第3轮结果分析：\\n- 数字：4, 4, 6, 6, 6\\n- 平均值 = 26/5 = 5.2\\n- 目标 = 5.2 × 0.5 = 2.6\\n- Player 1选4获胜，距离2.6差1.4\\n\\n关键观察：\\n1. 玩家分成两派：4和6，我选4与Player 1并列最低\\n2. 目标2.6远低于所有选择，说明大家还是高估了\\n3. 迭代继续：从~12降到~5，目标降到~2.6\\n\\n动态分析：\\n- 第1轮：选~22，目标~10.7\\n- 第2轮：选~12，目标~5.9  \\n- 第3轮：选~5.2，目标~2.6\\n\\n明显的收敛趋势！每次目标大约是选择的0.5倍。\\n\\n第4轮预测：\\n- 如果大家都理性，会选~2.6，目标~1.3\\n- 但Player 3/4/5选6，可能反应较慢或策略不同\\n- Player 1选4，和我一样，是敏锐的竞争者\\n\\n策略考量：\\n- 如果大家都降到2-3，目标1-1.5，我应该选1-2\\n- 但如果有玩家仍选5-6（惯性），目标会抬高到1.5-2\\n- Player 1是我的直接对手，他可能选2-3\\n\\n我选择2，这是一个既能应对快速收敛趋势，又不过度激进到0或1的策略。如果大家都理性降到2-3，目标1-1.5，我距离1.5差0.5；如果有人滞后选4-6，目标可能到2，我正好命中。\", \"number\": 2}\n```"
        },
        {
          "role": "user",
          "content": "上一轮（第 4 轮）结果：\nPlayer 1: 2\nPlayer 2: 2\nPlayer 3: 3\nPlayer 4: 3\nPlayer 5: 2\n当轮获胜者：Player 1。\n\n本轮是第 5 轮。请根据以上信息给出你的选择。"
        },
        {
          "role": "assistant",
          "content": " ```json\n{\"thought\": \"第4轮结果分析：\\n- 数字：2, 2, 3, 3, 2\\n- 平均值 = 12/5 = 2.4\\n- 目标 = 2.4 × 0.5 = 1.2\\n- Player 1选2获胜，距离1.2差0.8\\n\\n关键观察：\\n1. 选择分布：2,2,2,3,3 —— 高度集中在2-3\\n2. 目标1.2远低于选择，大家继续高估\\n3. 我和Player 1、Player 5都选2，Player 1获胜（可能随机或规则）\\n\\n收敛趋势加速：\\n- 第1轮：~22 → 目标~11\\n- 第2轮：~12 → 目标~6\\n- 第3轮：~5.2 → 目标~2.6\\n- 第4轮：~2.4 → 目标~1.2\\n\\n第5轮预测：\\n- 理性推断：大家会选~1.2，目标~0.6\\n- 实际行为：可能选0,1,2\\n- Player 1是强劲对手，可能选0或1\\n\\n博弈困境：\\n- 如果大家都选0-1，目标0-0.5，选0最好\\n- 但如果有人选2-3（惯性），目标抬高，选0就输了\\n\\n观察Player 3/4：从6→3，下降较慢，可能仍有惯性\\n\\n我选择1，这是一个平衡策略：\\n- 比上一轮目标1.2略低，体现学习\\n- 不过度激进到0，防止有人选2-3拉高目标\\n- 如果大家都理性选0-1，目标0-0.5，我距离0.5差0.5\\n- 如果有人选2，目标0.7-0.8，我距离较近\", \"number\": 1}\n```"
        }
      ]
    },
    {
      "name": "Player 3",
      "messages": [
        {
          "role": "user",
          "content": "第 1 轮：请给出你的选择（JSON 格式：{\"thought\": \"...\", \"number\": 整数}）。"
        },
        {
          "role": "assistant",
          "content": " ```json\n{\"thought\": \"这是第1轮，没有任何历史信息。我需要分析这个博弈：\\n\\n目标值 = 0.5 × (五人数字平均值) = 0.5 × (总和/5) = 总和/10\\n\\n如果所有5名玩家都随机选择0-100，平均值约50，目标值约25。\\n\\n但这是一个典型的\\\"选美竞赛\\\"博弈（凯恩斯选美竞赛）：\\n- 第一层思维：随机选，目标≈25\\n- 第二层思维：别人也这么想，大家都选25，目标≈12.5\\n- 第三层思维：别人也这么想，大家都选12.5，目标≈6.25\\n- ... 收敛到0\\n\\n然而现实中，玩家不会完全理性迭代到0。通常实验结果在20-30之间。\\n\\n作为Player 3，我需要在第一轮建立信息。选择一个中等偏低的数字，既不太激进（选0），也不太保守（选50）。\\n\\n考虑到：\\n- 如果有玩家选0-10的极端低值，会拉低平均值\\n- 如果有玩家选50+的高值，会拉高平均值\\n- 最可能的情况是多数人选择20-40区间\\n\\n我选择25，这是一个经典的第一轮策略，位于第一层和第二层思维的中间位置。\", \"number\": 25}\n```"
        },
        {
          "role": "user",
          "content": "上一轮（第 1 轮）结果：\nPlayer 1: 22\nPlayer 2: 22\nPlayer 3: 25\nPlayer 4: 18\nPlayer 5: 20\n当轮获胜者：Player 4。\n\n本轮是第 2 轮。请根据以上信息给出你的选择。"
        },
        {
          "role": "assistant",
          "content": " ```json\n{\"thought\": \"分析第1轮结果：\\n- 数字：22, 22, 25, 18, 20\\n- 总和：107\\n- 平均值：21.4\\n- 目标值：0.5 × 21.4 = 10.7\\n- 获胜者：Player 4（选18，距离10.7差7.3）\\n\\n关键观察：\\n1. 所有玩家都选择了相对理性的中低数字（18-25），没有人选极端高值\\n2. 目标值10.7远低于所有人的选择，说明大家都高估了\\n3. 最接近的是Player 4的18，但仍偏高\\n\\n这说明玩家们在第一层思维（目标≈25）附近，但实际目标更低。\\n\\n第2轮预测：\\n- 玩家们会意识到目标比预期低，可能向下调整\\n- 如果大家都选上一轮目标值附近（10-12），新目标≈5-6\\n- 但玩家可能不会一步调整到位\\n\\n策略选择：\\n- 保守：选10-12（基于上一轮实际目标）\\n- 激进：选5-8（预测别人会下调）\\n- 我选12，略低于上一轮实际目标10.7，但高于极端预测，平衡风险\", \"number\": 12}\n```"
        },
        {
          "role": "user",
          "content": "上一轮（第 2 轮）结果：\nPlayer 1: 12\nPlayer 2: 10\nPlayer 3: 12\nPlayer 4: 12\nPlayer 5: 13\n当轮获胜者：Player 2。\n\n本轮是第 3 轮。请根据以上信息给出你的选择。"
        },
        {
          "role": "assistant",
          "content": " ```json\n{\"thought\": \"分析第2轮结果：\\n- 数字：12, 10, 12, 12, 13\\n- 总和：59\\n- 平均值：11.8\\n- 目标值：0.5 × 11.8 = 5.9\\n- 获胜者：Player 2（选10，距离5.9差4.1）\\n\\n关键观察：\\n1. 所有玩家都大幅下调到10-13区间，非常集中\\n2. 但实际目标值5.9远低于所有人的选择\\n3. 又一次集体高估！这说明收敛速度比预期慢\\n4. Player 2选10获胜，虽然仍偏高，但相对最接近\\n\\n模式识别：\\n- 第1轮：目标≈10.7，大家选18-25\\n- 第2轮：目标≈5.9，大家选10-13\\n- 两轮都是实际目标 ≈ 大家选择的0.5倍左右\\n\\n第3轮预测：\\n- 玩家会继续下调，可能集中到5-8区间\\n- 如果大家都选5-8，平均值6.5，目标≈3.25\\n- 但需要判断收敛速度\\n\\n策略选择：\\n- 如果选6-7：假设别人选5-8，可能偏高\\n- 如果选3-4：假设别人充分理性，风险较大\\n- 我选6，略保守，考虑到玩家可能不会一步调到理论最优\", \"number\": 6}\n```"
        },
        {
          "role": "user",
          "content": "上一轮（第 3 轮）结果：\nPlayer 1: 4\nPlayer 2: 4\nPlayer 3: 6\nPlayer 4: 6\nPlayer 5: 6\n当轮获胜者：Player 1。\n\n本轮是第 4 轮。请根据以上信息给出你的选择。"
        },
        {
          "role": "assistant",
          "content": " ```json\n{\"thought\": \"分析第3轮结果：\\n- 数字：4, 4, 6, 6, 6\\n- 总和：26\\n- 平均值：5.2\\n- 目标值：0.5 × 5.2 = 2.6\\n- 获胜者：Player 1（选4，距离2.6差1.4）\\n\\n关键观察：\\n1. 玩家分化：Player 1和2选4，Player 3、4、5选6\\n2. 实际目标2.6，最接近的是4（仍偏高）\\n3. 又一次集体高估，但差距缩小了\\n4. 我选6，距离2.6差3.4，表现较差\\n\\n模式分析：\\n- 第1轮目标≈10.7，第2轮目标≈5.9，第3轮目标≈2.6\\n- 目标值在快速下降，接近0\\n- 玩家选择：25→12→6→4，也在收敛\\n\\n第4轮预测：\\n- 玩家会继续下调，可能选2-4\\n- 如果大家都选2-4，平均值3，目标≈1.5\\n- 如果有人激进选0-1，目标会更低\\n\\n策略困境：\\n- 选太低（0-1）：如果别人选3-4，平均值高，目标≈2，我输\\n- 选中等（2-3）：平衡选择\\n- 选偏高（4+）：可能再次高估\\n\\n考虑到玩家收敛速度，我选3。假设别人选2-4，平均值3，目标1.5，我距离1.5差1.5，有竞争力。\", \"number\": 3}\n```"
        },
        {
          "role": "user",
          "content": "上一轮（第 4 轮）结果：\nPlayer 1: 2\nPlayer 2: 2\nPlayer 3: 3\nPlayer 4: 3\nPlayer 5: 2\n当轮获胜者：Player 1。\n\n本轮是第 5 轮。请根据以上信息给出你的选择。"
        },
        {
          "role": "assistant",
          "content": " ```json\n{\"thought\": \"分析第4轮结果：\\n- 数字：2, 2, 3, 3, 2\\n- 总和：12\\n- 平均值：2.4\\n- 目标值：0.5 × 2.4 = 1.2\\n- 获胜者：Player 1（选2，距离1.2差0.8）\\n\\n关键观察：\\n1. 玩家高度集中：2或3，非常理性\\n2. 目标值1.2，最接近的是2（仍略高）\\n3. 我选3，距离1.2差1.8，表现一般\\n4. 连续4轮目标值都低于所有人的选择\\n\\n模式分析：\\n- 目标序列：10.7 → 5.9 → 2.6 → 1.2，快速趋近于0\\n- 选择序列：22/25 → 12/13 → 4/6 → 2/3，也在收敛\\n- 但每次目标都略低于最低选择\\n\\n第5轮预测：\\n- 玩家会继续下调，可能选0-2\\n- 如果大家都选0-2，平均值1，目标≈0.5\\n- 如果选0的人变多，目标接近0\\n\\n策略选择：\\n- 选0：激进，但如果别人选1-2，平均值高，目标≈1，我输\\n- 选1：平衡，假设别人选0-2，平均值1，目标0.5，我距离0.5差0.5\\n- 选2：保守，可能再次高估\\n\\n考虑到玩家可能不会一步到0，我选1。这是理论最优附近的平衡选择。\", \"number\": 1}\n```"
        }
      ]
    },
    {
      "name": "Player 4",
      "messages": [
        {
          "role": "user",
          "content": "第 1 轮：请给出你的选择（JSON 格式：{\"thought\": \"...\", \"number\": 整数}）。"
        },
        {
          "role": "assistant",
          "content": "```json\n{\"thought\": \"这是第一轮游戏，没有任何历史数据可以参考。我需要分析这个博弈的结构：\\n\\n目标值 = 0.5 × (五人数之和 / 5) = (五人数之和) / 10\\n\\n这是一个典型的\\\"选美竞赛\\\"博弈。如果所有玩家都随机选择0-100，平均值约为50，目标值约为25。但理性玩家会意识到这一点，所以可能选择接近25的数字。然而如果大家都选25，平均值就是25，目标值就是12.5...\\n\\n这种迭代推理会收敛到0（纳什均衡）。但实际游戏中，玩家不会完全理性，第一轮通常会在某个中间值。\\n\\n作为Player 4，我需要在第一次尝试一个合理的估计。考虑到：\\n1. 新手可能直接选50左右\\n2. 有一定思考的玩家可能选25左右\\n3. 深度思考的玩家可能选更低\\n\\n我猜测第一轮平均值可能在30-40之间，目标值在15-20之间。我选择18，这是一个保守的估计，既不太高（避免大家都理性选低值时我过高），也不太低（避免大家随机选时我过低）。\", \"number\": 18}\n```"
        },
        {
          "role": "user",
          "content": "上一轮（第 1 轮）结果：\nPlayer 1: 22\nPlayer 2: 22\nPlayer 3: 25\nPlayer 4: 18\nPlayer 5: 20\n当轮获胜者：Player 4。\n\n本轮是第 2 轮。请根据以上信息给出你的选择。"
        },
        {
          "role": "assistant",
          "content": "```json\n{\"thought\": \"第1轮结果分析：\\n- 五人数之和：22 + 22 + 25 + 18 + 20 = 107\\n- 平均值：107 / 5 = 21.4\\n- 目标值：0.5 × 21.4 = 10.7\\n- 我的选择18，距离10.7差7.3，但其他玩家选择更高，所以我反而最接近获胜了\\n\\n有趣！其他玩家（1,2,3,5）都选择了20-25的范围，明显没有进行深度推理，或者他们认为别人会选50所以目标值是25。\\n\\n第2轮策略：\\n- 其他玩家看到我赢了，可能会调整策略\\n- 如果他们意识到目标值应该更低，可能会降低选择\\n- 但如果他们只是模仿，可能继续选20-25\\n\\n假设其他玩家稍微理性化一点，可能选择15-22的范围。如果他们都选20左右，平均值20，目标值10。\\n\\n但我赢了上一轮，其他玩家可能注意到我的18是最低的，可能会向下调整。如果大家都往低处走，目标值会更低。\\n\\n我猜测这一轮平均值可能在15-18之间，目标值在7.5-9之间。我选择12，比上一轮低，但不过低（防止大家还是不够理性）。\", \"number\": 12}\n```"
        },
        {
          "role": "user",
          "content": "上一轮（第 2 轮）结果：\nPlayer 1: 12\nPlayer 2: 10\nPlayer 3: 12\nPlayer 4: 12\nPlayer 5: 13\n当轮获胜者：Player 2。\n\n本轮是第 3 轮。请根据以上信息给出你的选择。"
        },
        {
          "role": "assistant",
          "content": " ```json\n{\"thought\": \"第2轮结果分析：\\n- 五人数之和：12 + 10 + 12 + 12 + 13 = 59\\n- 平均值：59 / 5 = 11.8\\n- 目标值：0.5 × 11.8 = 5.9\\n- Player 2选择10，距离5.9差4.1，获胜\\n\\n关键观察：\\n1. 所有玩家都大幅降低了选择（从20-25降到10-13）！这说明大家都在学习和适应\\n2. 我的12虽然比上一轮低，但还是太高了，目标值只有5.9\\n3. Player 2的10最接近，但即使10也偏高\\n\\n第3轮策略：\\n- 现在大家意识到目标值应该更低，可能会继续降低\\n- 如果大家都选6-10，平均值8，目标值4\\n- 如果大家都更激进，可能选3-7，平均值5，目标值2.5\\n\\n这是一个收敛过程，向纳什均衡0靠近。但玩家不会一步到位选0。\\n\\n我需要预判其他人的调整幅度。看到目标值只有5.9，大家可能会选4-8的范围。\\n如果选5-8，平均值6.5，目标值3.25。\\n\\n我选择6，这是一个中等偏保守的估计，既反映了向下的趋势，又不过度激进（防止有人还没反应过来）。\", \"number\": 6}\n```"
        },
        {
          "role": "user",
          "content": "上一轮（第 3 轮）结果：\nPlayer 1: 4\nPlayer 2: 4\nPlayer 3: 6\nPlayer 4: 6\nPlayer 5: 6\n当轮获胜者：Player 1。\n\n本轮是第 4 轮。请根据以上信息给出你的选择。"
        },
        {
          "role": "assistant",
          "content": " ```json\n{\"thought\": \"第3轮结果分析：\\n- 五人数之和：4 + 4 + 6 + 6 + 6 = 26\\n- 平均值：26 / 5 = 5.2\\n- 目标值：0.5 × 5.2 = 2.6\\n- Player 1和2选择4，距离2.6差1.4，获胜（并列）\\n\\n关键观察：\\n1. 继续向低收敛！Player 1和2已经降到4，我、3、5选6\\n2. 目标值只有2.6，说明即使4还是偏高了\\n3. 现在有两名玩家（1、2）领先，他们可能会继续降低或保持低位\\n\\n第4轮策略：\\n- 收敛趋势明显，目标值会越来越低\\n- 如果大家都意识到目标值约2.6，可能选择2-4\\n- 如果选3-5，平均值4，目标值2\\n- Player 1和2赢了，可能继续选低或保持4\\n- 其他玩家（3、5和我）看到4获胜，可能也会降低\\n\\n预测：这一轮选择可能在2-5之间，平均值3-4，目标值1.5-2\\n\\n我需要比上一轮更低，但不能过低（防止有人还没跟上）。选择3是一个合理的估计，如果平均值是6（有人滞后），目标值3；如果平均值更低，目标值也更低。3比4更接近可能的低位目标值。\", \"number\": 3}\n```"
        },
        {
          "role": "user",
          "content": "上一轮（第 4 轮）结果：\nPlayer 1: 2\nPlayer 2: 2\nPlayer 3: 3\nPlayer 4: 3\nPlayer 5: 2\n当轮获胜者：Player 1。\n\n本轮是第 5 轮。请根据以上信息给出你的选择。"
        },
        {
          "role": "assistant",
          "content": " ```json\n{\"thought\": \"第4轮结果分析：\\n- 五人数之和：2 + 2 + 3 + 3 + 2 = 12\\n- 平均值：12 / 5 = 2.4\\n- 目标值：0.5 × 2.4 = 1.2\\n- Player 1、2、5选择2，距离1.2差0.8，获胜（并列）\\n\\n关键观察：\\n1. 极度收敛！三名玩家选2，两名选3\\n2. 目标值只有1.2，说明2还是偏高\\n3. 现在3名玩家领先，他们可能继续降低\\n\\n第5轮策略：\\n- 趋势是向0收敛，但速度在减缓\\n- 如果大家都选2，平均值2，目标值1\\n- 如果三名获胜者降到1，其他人选2，平均值1.4，目标值0.7\\n- 如果大家都降到1，平均值1，目标值0.5\\n\\n关键问题：玩家会降到0或1吗？还是停留在2？\\n- 选0是纳什均衡，但风险大（如果别人选高，目标值高，0就输了）\\n- 选1是安全且进取的选择\\n- 选2可能过于保守\\n\\n预测：这一轮可能在0-2之间，平均值1-1.5，目标值0.5-0.75\\n\\n我选择1。如果大家都理性，目标值约0.5-1，1最接近；如果有人还选2，目标值约1.2，1也最接近。1比2更接近预期的低位目标值，又比0安全（防止有人滞后选2-3）。\", \"number\": 1}\n```"
        }
      ]
    },
    {
      "name": "Player 5",
      "messages": [
        {
          "role": "user",
          "content": "第 1 轮：请给出你的选择（JSON 格式：{\"thought\": \"...\", \"number\": 整数}）。"
        },
        {
          "role": "assistant",
          "content": "```json\n{\"thought\": \"这是第一轮游戏，没有任何历史信息可以参考。我需要分析这个博弈的结构：\\n\\n目标值 = 0.5 × (五人平均值) = 0.5 × (总和/5) = 总和/10\\n\\n如果所有玩家都随机选择0-100的数字，平均值大约是50，那么目标值大约是25。\\n\\n但这是一个典型的\\\"选美竞赛\\\"式博弈——玩家会推理其他玩家怎么选。理性推理链条：\\n- 如果大家都选50，目标=25\\n- 如果大家都意识到这一点而选25，目标=12.5\\n- 继续推理下去会趋向于0\\n\\n然而在实际实验中，玩家通常不会完全理性地推到0。常见的均衡点在20-35之间。\\n\\n作为Player 5，我没有其他玩家的信息。稳妥策略是选择一个中等偏低的数字，既不过高也不过低。考虑到：\\n- 完全随机的话目标≈25\\n- 有一定理性的话目标会更低\\n- 我需要猜测其他4个玩家的理性程度\\n\\n选择20是一个相对均衡的策略：低于 naive 的25，但不过度理性地选太低的数字。这样无论其他玩家偏理性还是偏随机，都有一定竞争力。\", \"number\": 20}\n```"
        },
        {
          "role": "user",
          "content": "上一轮（第 1 轮）结果：\nPlayer 1: 22\nPlayer 2: 22\nPlayer 3: 25\nPlayer 4: 18\nPlayer 5: 20\n当轮获胜者：Player 4。\n\n本轮是第 2 轮。请根据以上信息给出你的选择。"
        },
        {
          "role": "assistant",
          "content": " ```json\n{\"thought\": \"上一轮结果分析：\\n- 数字：22, 22, 25, 18, 20（我）\\n- 总和 = 107，平均值 = 21.4，目标 = 10.7\\n- Player 4 选18获胜，最接近10.7\\n\\n关键发现：\\n1. 所有玩家都选了18-25的偏低数字，说明大家都做了一定理性推理（没有选50附近的naive数字）\\n2. 但目标值10.7比所有人的选择都低！说明大家还是\\\"不够理性\\\"——理性推理应该推到更低\\n3. Player 4选18最接近，但即使18也远高于目标10.7\\n\\n博弈论分析：\\n- 如果所有人继续类似的理性程度（选15-25范围），平均值约20，目标约10\\n- 但如果有人意识到这一点，应该选10左右\\n- 进一步：如果大家都意识到要往10靠，目标会更低...\\n\\n策略考量：\\n- 上一轮大家集中在18-25，这次可能会向下调整\\n- 如果我假设大家会降到15-20范围，平均值约17，目标约8.5\\n- 但如果我过度推理选太低（如5），而其他人只降到15，目标7.5，我选5反而离得远\\n\\n稳妥策略：比上一轮最低值18再低一些，但不要过度。选12-15范围。我选择13，既体现向下调整的趋势，又不过度理性。\", \"number\": 13}\n```"
        },
        {
          "role": "user",
          "content": "上一轮（第 2 轮）结果：\nPlayer 1: 12\nPlayer 2: 10\nPlayer 3: 12\nPlayer 4: 12\nPlayer 5: 13\n当轮获胜者：Player 2。\n\n本轮是第 3 轮。请根据以上信息给出你的选择。"
        },
        {
          "role": "assistant",
          "content": " ```json\n{\"thought\": \"上一轮结果分析：\\n- 数字：12, 10, 12, 12, 13（我）\\n- 总和 = 59，平均值 = 11.8，目标 = 5.9\\n- Player 2 选10获胜，最接近5.9\\n\\n关键发现：\\n1. 大家显著向下调整！从18-25降到了10-13\\n2. 但目标5.9仍然比所有人的选择都低\\n3. 我选13是最高值，离目标最远，表现最差\\n4. Player 2选10最接近，但10仍比5.9高\\n\\n动态分析：\\n- 两轮下来，目标值从10.7降到5.9，持续下降\\n- 玩家们在学习，但学习速度不够快，始终高于目标\\n- 如果这种趋势继续，大家会进一步下调\\n\\n预测本轮：\\n- 如果大家都意识到目标约6，可能选6-10范围\\n- 但如果大家都选7-8，平均值7.5，目标3.75\\n- 如果过度内卷，可能推到更低\\n\\n策略选择：\\n- 保守：选6-7，假设大家降到8-10\\n- 激进：选3-4，假设大家充分理性\\n- 上一轮大家从18降到10（降幅约45%），如果同比例降，可能到5-6\\n\\n我选择6：比上一轮目标5.9略高，假设大家会接近但未完全达到理性均衡。这样既跟上下降趋势，又不过度超前。\", \"number\": 6}\n```"
        },
        {
          "role": "user",
          "content": "上一轮（第 3 轮）结果：\nPlayer 1: 4\nPlayer 2: 4\nPlayer 3: 6\nPlayer 4: 6\nPlayer 5: 6\n当轮获胜者：Player 1。\n\n本轮是第 4 轮。请根据以上信息给出你的选择。"
        },
        {
          "role": "assistant",
          "content": " ```json\n{\"thought\": \"上一轮结果分析：\\n- 数字：4, 4, 6, 6, 6（我）\\n- 总和 = 26，平均值 = 5.2，目标 = 2.6\\n- Player 1 和 Player 2 选4获胜，最接近2.6\\n\\n关键发现：\\n1. 目标值降到2.6，非常低！\\n2. 我选6，离目标较远，表现不好\\n3. Player 1和2选4，最接近2.6\\n4. 数字分布：4（2人）, 6（3人），出现明显分层\\n\\n趋势分析：\\n- 目标值：10.7 → 5.9 → 2.6，持续快速下降\\n- 玩家选择：18-25 → 10-13 → 4-6，降幅加大\\n- 但即使选4，仍高于目标2.6\\n\\n预测本轮：\\n- 大家会意识到目标在2-3附近\\n- 如果都理性选择2-3，平均值2.5，目标1.25\\n- 如果选1-2，平均值1.5，目标0.75\\n- 继续推到极限会趋向0\\n\\n博弈困境：\\n- 选太低（0-1）：如果其他人没这么激进，目标较高，我会输\\n- 选中等（2-3）：平衡策略\\n- 选较高（4+）：可能重复上一轮错误\\n\\n观察Player 1和2：他们连续两轮表现好（第2轮10，第3轮4），说明他们调整更快。\\n\\n策略：选择2。理由：\\n- 上一轮目标2.6，选4获胜\\n- 如果同比例下降，目标约1.3\\n- 选2比目标略高，假设大家不会完全推到0\\n- 同时跟上领先者(Player 1,2)的快速下调节奏\", \"number\": 2}\n```"
        },
        {
          "role": "user",
          "content": "上一轮（第 4 轮）结果：\nPlayer 1: 2\nPlayer 2: 2\nPlayer 3: 3\nPlayer 4: 3\nPlayer 5: 2\n当轮获胜者：Player 1。\n\n本轮是第 5 轮。请根据以上信息给出你的选择。"
        },
        {
          "role": "assistant",
          "content": " ```json\n{\"thought\": \"上一轮结果分析：\\n- 数字：2, 2, 3, 3, 2（我）\\n- 总和 = 12，平均值 = 2.4，目标 = 1.2\\n- Player 1, 2, 5（我）选2获胜，最接近1.2\\n\\n关键发现：\\n1. 我选2，与Player 1, 2并列获胜！\\n2. 目标1.2，选2仍比目标高，但已经是整数中最接近的（选1的话差0.8，选2差0.8，相同）\\n3. 数字分布：2（3人）, 3（2人），非常集中\\n4. 目标值持续下降：10.7 → 5.9 → 2.6 → 1.2\\n\\n趋势分析：\\n- 降幅趋缓：从10.7到5.9（降4.8），5.9到2.6（降3.3），2.6到1.2（降1.4）\\n- 玩家选择已接近极限，难以再大幅下调\\n- 当前选择2-3，目标1.2，差距已经很小\\n\\n预测本轮：\\n- 如果大家都意识到目标约1，可能选0-2\\n- 如果选0,1,1,1,2，平均值1，目标0.5\\n- 如果选0,0,1,1,2，平均值0.8，目标0.4\\n- 极限情况趋向0\\n\\n博弈考量：\\n- Player 1和2连续多轮领先，他们很可能继续下调到0或1\\n- 如果我选2，而他们都选0或1，目标变低，我输\\n- 如果我选0，而大家选1-2，目标约1，我输\\n- 选1是平衡：无论大家选0,1,2，都有竞争力\\n\\n策略：选择1。理由：\\n- 上一轮目标1.2，选2获胜但已临界\\n- 领先者(Player 1,2)可能继续下调到0或1\\n- 选1比2更优：若目标<1.5，1比2更接近\\n- 避免选0的极端风险，同时跟上下降趋势\", \"number\": 1}\n```"
        }
      ]
    }
  ]
}